LICENSE
MANIFEST.in
README.rst
setup.py
helga_koji/__init__.py
helga_koji/colorize.py
helga_koji/colors.py
helga_koji/util.py
helga_koji.egg-info/PKG-INFO
helga_koji.egg-info/SOURCES.txt
helga_koji.egg-info/dependency_links.txt
helga_koji.egg-info/entry_points.txt
helga_koji.egg-info/requires.txt
helga_koji.egg-info/top_level.txt
helga_koji/actions/__init__.py
helga_koji/actions/get_build.py
helga_koji/actions/get_package.py
helga_koji/actions/kojiweb.py
helga_koji/actions/user_tasks.py
helga_koji/signals/__init__.py
helga_koji/signals/build.py
helga_koji/signals/task.py
helga_koji/signals/util.py
helga_koji/tests/__init__.py
helga_koji/tests/test_colorize.py
helga_koji/tests/test_user_tasks.py
helga_koji/tests/test_util.py