Metadata-Version: 1.1
Name: helga-koji
Version: 1.7.0
Summary: Koji plugin for Helga
Home-page: https://github.com/ktdreyer/helga-koji
Author: ken dreyer
Author-email: ktdreyer@ktdreyer.com
License: MIT
Keywords: irc bot koji
Platform: UNKNOWN
Classifier: Development Status :: 4 - Beta
Classifier: License :: OSI Approved :: MIT License
Classifier: Intended Audience :: Developers
Classifier: Operating System :: POSIX
Classifier: Programming Language :: Python
Classifier: Topic :: Software Development
